botolib/__init__.py
botolib/services/__init__.py
botolib/services/apigateway.py
botolib/services/apigatewayv2.py
botolib/services/cloudformation.py
botolib/services/cloudwatch.py
botolib/services/cloudwatchlogs.py
botolib/services/dynamodb.py
botolib/services/eventbridge.py
botolib/services/iam.py
botolib/services/identitystore.py
botolib/services/iot.py
botolib/services/lambda_aws.py
botolib/services/resourcegroupstaggpingapi.py
botolib/services/s3.py
botolib/services/secretsmanager.py
botolib/services/sns.py
botolib/services/sqs.py
botolib/services/ssm.py
botolib/services/sso.py
botolib/services/ssoadmin.py
botolib/services/ssooidc.py
botolib/services/sts.py
botolib/utils/__init__.py
botolib/utils/chunk.py
botolib/utils/common.py
botolib/utils/logger.py
botolib/utils/retry.py
botolib-0.0.35.dist-info/LICENSE
botolib-0.0.35.dist-info/METADATA
botolib-0.0.35.dist-info/WHEEL
botolib-0.0.35.dist-info/top_level.txt
botolib-0.0.35.dist-info/RECORD
