Metadata-Version: 2.2
Name: botolib
Version: 0.0.35
Summary: A boto lib that enhances some aws service clients
Home-page: https://github.com/kejun91/botolib
Author: Jun Ke
Author-email: kejun91@gmail.com
Classifier: Programming Language :: Python :: 3
Classifier: License :: OSI Approved :: MIT License
Classifier: Operating System :: OS Independent
Requires-Python: >=3.9
License-File: LICENSE
Requires-Dist: boto3
Dynamic: author
Dynamic: author-email
Dynamic: classifier
Dynamic: description
Dynamic: description-content-type
Dynamic: home-page
Dynamic: requires-dist
Dynamic: requires-python
Dynamic: summary
